{"type":"FeatureCollection","features":[{"type":"Feature","properties":{"scalerank":8,"id":1079,"name":"Les 3 Vallées (Val Thorens, Les Menuires, St Martin De Belleville, Meribel, Brides-les-bains, La Tania, Courchevel)","status":"operating","activities":["downhill"],"official_website":"http://www.les3vallees.com"},"geometry":{"type":"Point","coordinates":[6.5972900390625,45.3757846894103]}}]}